Workbook

Sheet サマリー
B2: Stripe決済 手動テスト チェックリスト
B3: 対象: サインアップ決済 / プラン変更 / 解約 / 再契約 / 台本上限・ロック / アカウント削除の実機テスト
B6: 区分 | C6: 内容 | D6: 件数 | E6: OK | F6: NG | G6: 未実施 | H6: 進捗率
B7: SU | C7: サインアップ・決済（新規登録/planページ経由） | D7: =COUNTIF('テストケース一覧'!$B:$B,"SU*") | E7: =COUNTIFS('テストケース一覧'!$B:$B,"SU*",'テストケース一覧'!$J:$J,"OK") | F7: =COUNTIFS('テストケース一覧'!$B:$B,"SU*",'テストケース一覧'!$J:$J,"NG") | G7: =COUNTIFS('テストケース一覧'!$B:$B,"SU*",'テストケース一覧'!$J:$J,"未実施") | H7: =IF(D7=0,0,E7/D7)
B8: CH | C8: プラン変更（アップグレード・ダウングレード） | D8: =COUNTIF('テストケース一覧'!$B:$B,"CH*") | E8: =COUNTIFS('テストケース一覧'!$B:$B,"CH*",'テストケース一覧'!$J:$J,"OK") | F8: =COUNTIFS('テストケース一覧'!$B:$B,"CH*",'テストケース一覧'!$J:$J,"NG") | G8: =COUNTIFS('テストケース一覧'!$B:$B,"CH*",'テストケース一覧'!$J:$J,"未実施") | H8: =IF(D8=0,0,E8/D8)
B9: CN | C9: プラン解約 | D9: =COUNTIF('テストケース一覧'!$B:$B,"CN*") | E9: =COUNTIFS('テストケース一覧'!$B:$B,"CN*",'テストケース一覧'!$J:$J,"OK") | F9: =COUNTIFS('テストケース一覧'!$B:$B,"CN*",'テストケース一覧'!$J:$J,"NG") | G9: =COUNTIFS('テストケース一覧'!$B:$B,"CN*",'テストケース一覧'!$J:$J,"未実施") | H9: =IF(D9=0,0,E9/D9)
B10: RE | C10: プラン再契約 | D10: =COUNTIF('テストケース一覧'!$B:$B,"RE*") | E10: =COUNTIFS('テストケース一覧'!$B:$B,"RE*",'テストケース一覧'!$J:$J,"OK") | F10: =COUNTIFS('テストケース一覧'!$B:$B,"RE*",'テストケース一覧'!$J:$J,"NG") | G10: =COUNTIFS('テストケース一覧'!$B:$B,"RE*",'テストケース一覧'!$J:$J,"未実施") | H10: =IF(D10=0,0,E10/D10)
B11: DL | C11: ユーザー削除 | D11: =COUNTIF('テストケース一覧'!$B:$B,"DL*") | E11: =COUNTIFS('テストケース一覧'!$B:$B,"DL*",'テストケース一覧'!$J:$J,"OK") | F11: =COUNTIFS('テストケース一覧'!$B:$B,"DL*",'テストケース一覧'!$J:$J,"NG") | G11: =COUNTIFS('テストケース一覧'!$B:$B,"DL*",'テストケース一覧'!$J:$J,"未実施") | H11: =IF(D11=0,0,E11/D11)
B12: LK | C12: 台本上限・ロック（ダウングレード後の上限超過台本） | D12: =COUNTIF('テストケース一覧'!$B:$B,"LK*") | E12: =COUNTIFS('テストケース一覧'!$B:$B,"LK*",'テストケース一覧'!$J:$J,"OK") | F12: =COUNTIFS('テストケース一覧'!$B:$B,"LK*",'テストケース一覧'!$J:$J,"NG") | G12: =COUNTIFS('テストケース一覧'!$B:$B,"LK*",'テストケース一覧'!$J:$J,"未実施") | H12: =IF(D12=0,0,E12/D12)
B13: WH | C13: Webhook・データ整合性の確認 | D13: =COUNTIF('テストケース一覧'!$B:$B,"WH*") | E13: =COUNTIFS('テストケース一覧'!$B:$B,"WH*",'テストケース一覧'!$J:$J,"OK") | F13: =COUNTIFS('テストケース一覧'!$B:$B,"WH*",'テストケース一覧'!$J:$J,"NG") | G13: =COUNTIFS('テストケース一覧'!$B:$B,"WH*",'テストケース一覧'!$J:$J,"未実施") | H13: =IF(D13=0,0,E13/D13)
B14: 合計 | D14: =SUM(D7:D13) | E14: =SUM(E7:E13) | F14: =SUM(F7:F13) | G14: =SUM(G7:G13) | H14: =IF(D14=0,0,E14/D14)
B15: ※「テストケース一覧」シートの「実施結果」列(J列)を更新すると、この表は自動集計されます。
B17: シート構成
B18: ・テストケース一覧 | C18: 全テストケース本体（手順・期待結果・実施結果を記入）
B19: ・事前準備 | C19: テスト環境・Stripe CLI・Webhook確認方法のセットアップ手順
B20: ・Stripeテストカード | C20: 決済テストに使用するカード番号一覧
B21: ・ステージング（2026-10） | C21: リリース前の再テスト用。ステージング環境（devブランチ）で実施。疑似障害の5件はローカルで実施（M列「実施環境」）
B23: ステージング実施分（シート「ステージング（2026-10）」）
B24: 区分 | C24: 内容 | D24: 件数 | E24: OK | F24: NG | G24: 未実施 | H24: 進捗率
B25: SU | C25: サインアップ・決済（新規登録/planページ経由） | D25: =COUNTIF('ステージング（2026-10）'!$B:$B,"SU*") | E25: =COUNTIFS('ステージング（2026-10）'!$B:$B,"SU*",'ステージング（2026-10）'!$J:$J,"OK") | F25: =COUNTIFS('ステージング（2026-10）'!$B:$B,"SU*",'ステージング（2026-10）'!$J:$J,"NG") | G25: =COUNTIFS('ステージング（2026-10）'!$B:$B,"SU*",'ステージング（2026-10）'!$J:$J,"未実施") | H25: =IF(D25=0,0,E25/D25)
B26: CH | C26: プラン変更（アップグレード・ダウングレード） | D26: =COUNTIF('ステージング（2026-10）'!$B:$B,"CH*") | E26: =COUNTIFS('ステージング（2026-10）'!$B:$B,"CH*",'ステージング（2026-10）'!$J:$J,"OK") | F26: =COUNTIFS('ステージング（2026-10）'!$B:$B,"CH*",'ステージング（2026-10）'!$J:$J,"NG") | G26: =COUNTIFS('ステージング（2026-10）'!$B:$B,"CH*",'ステージング（2026-10）'!$J:$J,"未実施") | H26: =IF(D26=0,0,E26/D26)
B27: CN | C27: プラン解約 | D27: =COUNTIF('ステージング（2026-10）'!$B:$B,"CN*") | E27: =COUNTIFS('ステージング（2026-10）'!$B:$B,"CN*",'ステージング（2026-10）'!$J:$J,"OK") | F27: =COUNTIFS('ステージング（2026-10）'!$B:$B,"CN*",'ステージング（2026-10）'!$J:$J,"NG") | G27: =COUNTIFS('ステージング（2026-10）'!$B:$B,"CN*",'ステージング（2026-10）'!$J:$J,"未実施") | H27: =IF(D27=0,0,E27/D27)
B28: RE | C28: プラン再契約 | D28: =COUNTIF('ステージング（2026-10）'!$B:$B,"RE*") | E28: =COUNTIFS('ステージング（2026-10）'!$B:$B,"RE*",'ステージング（2026-10）'!$J:$J,"OK") | F28: =COUNTIFS('ステージング（2026-10）'!$B:$B,"RE*",'ステージング（2026-10）'!$J:$J,"NG") | G28: =COUNTIFS('ステージング（2026-10）'!$B:$B,"RE*",'ステージング（2026-10）'!$J:$J,"未実施") | H28: =IF(D28=0,0,E28/D28)
B29: DL | C29: ユーザー削除 | D29: =COUNTIF('ステージング（2026-10）'!$B:$B,"DL*") | E29: =COUNTIFS('ステージング（2026-10）'!$B:$B,"DL*",'ステージング（2026-10）'!$J:$J,"OK") | F29: =COUNTIFS('ステージング（2026-10）'!$B:$B,"DL*",'ステージング（2026-10）'!$J:$J,"NG") | G29: =COUNTIFS('ステージング（2026-10）'!$B:$B,"DL*",'ステージング（2026-10）'!$J:$J,"未実施") | H29: =IF(D29=0,0,E29/D29)
B30: LK | C30: 台本上限・ロック（ダウングレード後の上限超過台本） | D30: =COUNTIF('ステージング（2026-10）'!$B:$B,"LK*") | E30: =COUNTIFS('ステージング（2026-10）'!$B:$B,"LK*",'ステージング（2026-10）'!$J:$J,"OK") | F30: =COUNTIFS('ステージング（2026-10）'!$B:$B,"LK*",'ステージング（2026-10）'!$J:$J,"NG") | G30: =COUNTIFS('ステージング（2026-10）'!$B:$B,"LK*",'ステージング（2026-10）'!$J:$J,"未実施") | H30: =IF(D30=0,0,E30/D30)
B31: WH | C31: Webhook・データ整合性の確認 | D31: =COUNTIF('ステージング（2026-10）'!$B:$B,"WH*") | E31: =COUNTIFS('ステージング（2026-10）'!$B:$B,"WH*",'ステージング（2026-10）'!$J:$J,"OK") | F31: =COUNTIFS('ステージング（2026-10）'!$B:$B,"WH*",'ステージング（2026-10）'!$J:$J,"NG") | G31: =COUNTIFS('ステージング（2026-10）'!$B:$B,"WH*",'ステージング（2026-10）'!$J:$J,"未実施") | H31: =IF(D31=0,0,E31/D31)
B32: 合計 | D32: =SUM(D25:D31) | E32: =SUM(E25:E31) | F32: =SUM(F25:F31) | G32: =SUM(G25:G31) | H32: =IF(D32=0,0,E32/D32)

Sheet テストケース一覧
A1: No | B1: テストID | C1: 大分類 | D1: 前提条件 | E1: テスト手順 | F1: 期待結果（画面表示） | G1: 期待結果（DB: profile/subscription） | H1: 期待結果（Stripe側） | I1: 使用テストカード/備考 | J1: 実施結果 | K1: 実施日 | L1: 気づき・不具合メモ
A2: 1 | B2: SU-01 | C2: SU: サインアップ・決済 | D2: 未登録のメールアドレスを準備する。/plan または /sign-up にアクセスできる状態。 | E2: 1. /plan の無料プランで「無料で始める」を押す（または直接 /sign-up） 2. メールアドレス・パスワードを入力し「新規登録」を送信 | F2: エラーなく /protected へ遷移する | G2: ・auth.usersにユーザーが作成される ・profileにstripe_uuid/supabase_uuid/emailが登録される ・subscriptionにplan_id=フリー, price_id=null, status='active', stripe_subscription_id=nullで1行作成される | H2: Stripeに顧客(customer)が作成される（サブスクリプションは作成されない） | I2: カード入力なし | J2: OK
A3: 2 | B3: SU-02 | C3: SU: サインアップ・決済 | D3: 未ログイン状態。有料プランがStripeテストモードのPrice IDと紐づいて登録済みであること。 | E3: 1. /plan にアクセス（未ログイン） 2. 任意の有料プランの「今すぐ始める」を押す 3. /sign-up へ遷移することを確認し、メール・パスワードを入力して送信 4. Stripe Checkoutページでカード情報を入力し決済 | F3: 決済完了後、success_url（/protected?session_id=...）へリダイレクトされる。mypageのプラン表示が選択した有料プラン名になっている | G3: ・profile/subscription（フリー分）がまず作成される ・決済完了後、customer.subscription.created Webhookにより subscription 行が update され、plan_id=選択プラン, price_id, stripe_subscription_id, status='active', current_period_end, cancel_at_period_end=false になる | H3: Checkoutセッション完了、Subscriptionオブジェクトがactiveで作成される。metadata.user_idが正しく設定されていることを確認 | I3: 4242 4242 4242 4242（成功）／これが「planページからユーザー登録&決済」の本流フロー | J3: OK
A4: 3 | B4: SU-03 | C4: SU: サインアップ・決済 | D4: SU-02と同じ手順の直前まで進める | E4: Checkoutページで拒否カードを入力して決済を試みる | F4: Stripe Checkout画面上にカードエラーが表示され、決済が完了しない。ユーザーはCheckout画面に留まる | G4: subscription行はフリープランのまま更新されない（Webhookが発火しないため） | H4: PaymentIntent/Charge が失敗する。Subscriptionは作成されない | I4: 4000 0000 0000 0002（決済拒否） | J4: OK
A5: 4 | B5: SU-04 | C5: SU: サインアップ・決済 | D5: SU-02と同じ手順の直前まで進める | E5: Checkoutページで3Dセキュア認証が必要なカードを入力し、認証画面で認証を完了する | F5: 追加認証（3DS）画面が表示され、認証完了後に決済が成功し /protected へ遷移する | G5: customer.subscription.created Webhookにより subscription行が正しく更新される | H5: SubscriptionがactiveでStripe上に作成される | I5: 4000 0025 0000 3155（要3Dセキュア） | J5: OK
A6: 5 | B6: SU-05 | C6: SU: サインアップ・決済 | D6: SU-02と同じ手順の直前まで進める | E6: Checkoutページでブラウザバック、または「戻る」リンクで決済をキャンセルする | F6: cancel_urlである /plan へリダイレクトされる。エラー表示は出ない | G6: ユーザー・profile・subscription（フリー分）は作成済みのまま。有料プランへは更新されない | H6: Checkoutセッションはexpired/未完了のまま。Subscriptionは作成されない | I6: - | J6: OK
A7: 6 | B7: SU-06 | C7: SU: サインアップ・決済 | D7: 既に登録済みのメールアドレスを用意する | E7: そのメールアドレスで /sign-up から新規登録を試みる | F7: 「ユーザーはすでに存在しています。」がエラーメッセージとして表示される | G7: 新しいuser/profile/subscriptionは作成されない | H7: 新しいStripe顧客は作成されない | I7: - | J7: OK
A8: 7 | B8: SU-07 | C8: SU: サインアップ・決済 | D8: - | E8: メールアドレスまたはパスワードを空欄のまま新規登録を送信する（フロントのバリデーションを回避できる場合も想定） | F8: 「メールアドレスとパスワードを入力してください。」等のエラーが表示される | G8: 何も作成されない | H8: 何も作成されない | I8: フォームのZodバリデーションと合わせて確認 | J8: OK
A9: 8 | B9: SU-08 | C9: SU: サインアップ・決済 | D9: SU-01で作成したフリープランユーザーでログイン済み（＝「ユーザ作成後に決済」のケース） | E9: 1. ログイン状態で /plan（もしくはmypageの「プランを変更する」を経由せず直接）へアクセス 2. 有料プランの「このプランに変更する」を押す 3. Checkoutで決済を完了する | F9: 決済完了後 /protected へ遷移。mypageの現在のプランが有料プラン名に変わっている | G9: 既存のsubscription行（フリー分）がcustomer.subscription.created Webhookにより有料プラン情報でupdateされる（stripe_customer_idは既存のまま流用） | H9: 既存のcustomerに対してSubscriptionが新規作成される | I9: 4242 4242 4242 4242 | J9: OK
A10: 9 | B10: SU-09 | C10: SU: サインアップ・決済 | D10: SU-08と同じ前提 | E10: ログイン済みユーザーが有料プラン決済を拒否カードで試みる | F10: Checkout画面でエラー表示、決済不成立 | G10: subscription行は更新されない（フリーのまま） | H10: Subscriptionは作成されない | I10: 4000 0000 0000 0002 | J10: OK
A11: 10 | B11: SU-10 | C11: SU: サインアップ・決済 | D11: フリープランでログイン中。checkout()実行時にStripe API呼び出しが失敗する状況（テスト用に一時的にAPIキーを無効化する等で疑似的に再現） | E11: 有料プランの「このプランに変更する」を押す | F11: 「決済を開始できませんでした。時間をおいて再度お試しください。」がトースト表示される | G11: DBの状態は変化しない | H11: Checkoutセッションは作成されない | I11: 疑似障害での確認。本番同様の再現が難しい場合はコードレビューで代替可 | J11: OK
A12: 11 | B12: CH-01 | C12: CH: プラン変更 | D12: 有料プラン契約中のユーザーでログイン | E12: mypageで「プランを変更する」を押す | F12: /plan?planname=現在のプラン名 に遷移し、現在契約中のプランのボタンがdisabled（押せない）状態になっている | G12: 変化なし（画面確認のみ） | H12: 変化なし | I12: - | J12: OK
A13: 12 | B13: CH-02 | C13: CH: プラン変更 | D13: 有料プランA契約中（stripe_subscription_id保有）でログイン。プランB（上位プラン）が存在すること | E13: 1. mypage→「プランを変更する」で/planへ遷移 2. プランBの「このプランに変更する」を押す | F13: 処理完了後「サブスクリプションのアップグレードに成功しました」がトースト表示される。mypageのプラン表示がBに変わる | G13: customer.subscription.updated Webhookにより subscription 行が plan_id=B, price_id=B, current_period_end, cancel_at_period_end等で更新される | H13: 同一Subscriptionのitemがproration_behavior=create_prorationsで即時更新される。日割り請求(Invoice)が発生していることを確認 | I13: 画面上でカード入力は不要（既存の支払い方法で即時課金） | J13: OK | L13: 内部的（stripe/supabace）には変わるが、フロントの表示が変わらない。 レンダーが更新されないのでplanカードは前回のプランが非活性のままで、headerカードもプランが更新されない
A14: 13 | B14: CH-03 | C14: CH: プラン変更 | D14: 有料プランB契約中でログイン。下位プランAが存在すること | E14: /plan?planname=B でプランAの「このプランに変更する」（ダウングレード）を押す | F14: 「サブスクリプションのアップグレードに成功しました」表示。mypageのプラン表示がAに変わる | G14: subscription行がplan_id=A, price_id=Aへ更新される | H14: Subscription itemがAのpriceに変更され、日割りでクレジット（返金相当）が発生することを確認 | I14: - | J14: OK | L14: 内部的（stripe/supabace）には変わるが、フロントの表示が変わらない。 レンダーが更新されないのでplanカードは前回のプランが非活性のままで、headerカードもプランが更新されない
A15: 14 | B15: CH-04 | C15: CH: プラン変更 | D15: UpgradeSubscriptionが失敗する状況。次の2パターンを確認する (a) 無効なprice_id（planテーブルに無い／is_active=false）を一時的に渡す → Stripeを呼ぶ前のプラン検証で止まる (b) Stripe APIエラー（APIキーを一時的に無効化する等） | E15: プラン変更ボタンを押す | F15: 「サブスクリプションのアップグレードに失敗しました」がトースト表示される | G15: subscription行は更新されない | H15: Subscriptionは変更されない（(a)の場合はStripe APIも呼ばれず、日割り請求も発生しない） | I15: 疑似障害での確認 | J15: OK
A16: 15 | B16: CH-05 | C16: CH: プラン変更 | D16: 解約予約中（cancel_at_period_end=true）の有料プランユーザーでログイン | E16: 1. /plan で別の有料プランの「このプランに変更する」を押す 2. 確認ダイアログで「変更する」を押す | F16: ・確認ダイアログに「現在の解約予定は取り消され、プランは継続されます。料金の差額は日割りで請求されます。」と表示される ・変更後、トーストに成功メッセージが表示され、mypageに「解約予定日」ではなく「次回の支払い：」が表示される。プラン名は新プランになる ・確認ダイアログを閉じた場合は何も変わらない | G16: subscription行が plan_id=新プラン, price_id=新プラン, cancel_at_period_end=false に更新される | H16: Subscriptionのpriceが新プランになり、cancel_at_period_end=false（解約予定が取り消される）。差額の日割り請求が作成される | I16: UpgradeSubscriptionは価格変更と cancel_at_period_end: false を1回のAPI呼び出しで送る仕様 | J16: NG | L16: プランはアップデートされるが、解約状態は続く
A17: 16 | B17: CH-06 | C17: CH: プラン変更 | D17: CN-01完了後（解約予約中、cancel_at_period_end=true） | E17: 1. /plan を開く 2. 現在契約中のプランの「解約を解除する」を押す | F17: ・現在のプランのボタンが「解約を解除する」、フリープランのボタンが「ダウングレード予定」になっている ・押すと「サブスクリプションの再開に成功しました」が表示され、現在のプランのボタンが「現在のプラン」（押せない）に変わる | G17: subscription.cancel_at_period_end が false に更新される | H17: Subscriptionの cancel_at_period_end が false になる | I17: mypageの「解約を解除する」（RE-01）と同じ処理を /plan から実行するケース | J17: 未実施
A18: 17 | B18: CN-01 | C18: CN: プラン解約 | D18: 有料プラン契約中（stripe_subscription_id保有、cancel_at_period_end=false）でログイン | E18: 1. mypageで「プランを解約する」を押す 2. 確認ダイアログで「解約」を押す | F18: 「サブスクリプションを解約しました」表示。mypageが「解約予定日：〇〇」表示と「解約を解除する」ボタンに切り替わる | G18: subscription.cancel_at_period_end が true に更新される（レコード自体はまだ削除されない） | H18: StripeのSubscriptionがcancel_at_period_end=trueになる（ステータスはまだactive） | I18: - | J18: OK
A19: 18 | B19: CN-02 | C19: CN: プラン解約 | D19: CN-01と同じ前提 | E19: 「プランを解約する」→確認ダイアログで「キャンセル」（閉じる）を押す | F19: 画面は変化せず、通常のプラン表示のまま | G19: subscription行は変化しない | H19: Stripe側も変化しない | I19: 誤操作防止の確認 | J19: OK
A20: 19 | B20: CN-03 | C20: CN: プラン解約 | D20: Unsubscription呼び出し時にStripe APIエラーが起きる状況（無効なstripe_subscription_idを一時的にセットする等） | E20: 解約を実行する | F20: 「サブスクリプションの解約に失敗しました」がトースト表示される | G20: subscription行は更新されない | H20: Stripe側も変化しない | I20: 疑似障害での確認 | J20: OK
A21: 20 | B21: CN-04 | C21: CN: プラン解約 | D21: CN-01完了後（cancel_at_period_end=trueの状態） | E21: １.Stripe CLI で Webhook を転送しておく（stripe listen --forward-to localhost:3000/api/stripe/webhook） ２.次のどちらかで解約を確定させる ・Test Clocks で、期間終了より後まで時間を進める（本来の流れ） ・Stripe ダッシュボード（テストモード）で、該当するサブスクを「今すぐキャンセル」する（簡易確認） ※ stripe trigger customer.subscription.deleted は DB の行と紐付かないため、代わりの手段にはならない | F21: ・mypage の現在のプランがフリープランの名前になる。「次回の支払い：支払いなし」と表示され、「プランを解約する」ボタンが表示されない ・/plan ではフリープランが「現在のプラン」、有料プランが「このプランに変更する」になる ・台本がフリープランの上限より多い場合、作成日が新しい順に上限数までが使え、残りはロック表示になる（削除だけできる） | G21: subscription の行がフリープランに更新される plan_id=フリー、stripe_subscription_id / price_id / current_period_end=null、cancel_at_period_end=false | H21: Stripe の Subscription が status='canceled' になる | I21: 期間の経過をともなう、本来の解約確定の流れ。Test Clocks を使わない場合は、ダッシュボードの「今すぐキャンセル」で代わりに確認する | J21: OK | L21: subscriptionテーブルの行自体を消すのでフリープランに変更するようにする
A22: 21 | B22: RE-01 | C22: RE: プラン再契約 | D22: CN-01完了後（解約予約中、cancel_at_period_end=true、まだ契約期間内） | E22: mypageで「解約を解除する」を押す | F22: 「サブスクリプションの再開に成功しました」表示。「解約予定日」表示が消え、通常の「次回の支払い：」表示に戻る | G22: subscription.cancel_at_period_endがfalseに更新される | H22: StripeのSubscriptionのcancel_at_period_endがfalseに戻る（Subscription自体は継続していたので新規決済は発生しない） | I22: - | J22: OK | L22: 「プランを再開する」に成功したらレンダーを更新する（マイページとheaderも更新）
A23: 22 | B23: RE-02 | C23: RE: プラン再契約 | D23: ReactivateSubscription呼び出し時にStripe APIエラーが起きる状況 | E23: 「解約を解除する」を押す | F23: 「サブスクリプションの再開に失敗しました」表示 | G23: subscription行は更新されない | H23: Stripe側も変化しない | I23: 疑似障害での確認 | J23: OK
A24: 23 | B24: RE-03 | C24: RE: プラン再契約 | D24: CN-04 が完了し、subscription の行がフリープランに戻ったユーザー（stripe_subscription_id=null）でログインしている | E24: 1. mypage の「プランを変更する」、または /plan から、有料プランの「このプランに変更する」を押し、Checkout で決済する 2. 決済が終わったら、DB と Stripe を確認する | F24: 決済完了後 /protected に戻り、mypageのプラン表示が新しい有料プラン名になっている | G24: ★確認ポイント：customer.subscription.created の Webhook によって、既存の subscription の行が update され、plan_id=選んだプラン、price_id、stripe_subscription_id=新しい ID、status='active'、current_period_end、cancel_at_period_end=false になる | H24: 既存customerに対して新しいSubscriptionが作成される | I24: 解約が確定したあとの再契約の流れ。新しい Stripe Subscription が同じ customer に作られ、DB の行が更新されることを確認する | J24: OK | L24: 有料プラン解約した後subscripionテーブルを削除せず、freeプランに戻す。 でないと、RLSの作成上限に引っかかり台本を作れなくなる
A25: 24 | B25: RE-04 | C25: RE: プラン再契約 | D25: RE-01またはRE-03完了直後 | E25: mypageのプラン情報（現在のプラン名、次回支払い日、台本数上限）を確認する | F25: 契約中のプラン名・次回支払日（current_period_end）・max_scriptsが正しい値で表示されている | G25: subscriptionとplanのjoin結果（userPlan）が最新の状態になっている | H25: Stripeダッシュボードの請求情報と日時が一致している（日本時間表記であることも確認） | I25: - | J25: OK | L25: プランをアップグレードしたときにsubscripionテーブルのstatus:incompleteになってしまうので直す。 でないと、RLSの作成上限に引っかかり台本を作れなくなる
A26: 25 | B26: LK-01 | C26: LK: 台本上限・ロック | D26: 有料プランで、フリープランの上限（max_scripts）より多い台本を作成済み。CN-04で解約を確定させた（または下位プランに変更した）直後 | E26: 台本一覧（/protected）を開く | F26: ・作成日が新しい順に上限数までの台本は通常表示 ・それより古い台本は薄く表示され、鍵アイコンと「プランをアップグレード」「削除」ボタンだけが表示される（編集・プロンプター表示・タイトル変更はできない） | G26: script行は削除・変更されない（ロックは表示時に計算するだけでDBには持たない） | H26: - | I26: 作成日（inserted_at）が新しい順に有効になる。更新日ではない点に注意 | J26: 未実施
A27: 26 | B27: LK-02 | C27: LK: 台本上限・ロック | D27: LK-01の状態 | E27: 1. ロック中の台本のIDを控え、/protected/script/edit/{id} を直接開く 2. /protected/script/prompter/{id} を直接開く | F27: どちらも「この台本はロックされています。上位プランにアップデートしてください。」が表示され、台本の内容は表示されない | G27: 変化なし | H27: - | I27: サーバー側（getEditScript）での拒否の確認。editScript／editScriptNameもロック中は更新を拒否する | J27: 未実施
A28: 27 | B28: LK-03 | C28: LK: 台本上限・ロック | D28: LK-01の状態 | E28: 使える状態（ロックされていない）の台本を1件削除する | F28: ロック中だった台本のうち、作成日が一番新しい1件のロックが外れ、通常表示になる | G28: 削除した台本の行だけが削除される | H28: - | I28: - | J28: 未実施
A29: 28 | B29: LK-04 | C29: LK: 台本上限・ロック | D29: LK-01の状態 | E29: /plan から有料プランに再契約する（RE-03の手順） | F29: 上限が上がり、ロック中だった台本が通常表示に戻る（無制限プランなら全件）。編集・プロンプター表示ができる | G29: script行は変化しない（ロック情報はDBに持たないため） | H29: - | I29: - | J29: 未実施
A30: 29 | B30: LK-05 | C30: LK: 台本上限・ロック | D30: フリープランで、台本数が上限（max_scripts）に達している | E30: 1. 台本一覧（/protected）を開く 2. （任意）createScriptを直接実行する等で作成を試みる | F30: ・「新規作成」ボタンの代わりに「プランをアップグレード」ボタンと上限到達の案内文が表示される ・createScriptを直接実行した場合は「台本の作成上限に達しています。プランをアップグレードしてください。」が返る | G30: RLSによりscript行は追加されない（エラーコード42501） | H30: - | I30: 作成上限はSupabaseのRLSで制御している | J30: 未実施
A31: 30 | B31: DL-01 | C31: DL: ユーザー削除 | D31: 有料プラン契約中（アクティブなStripe Subscriptionあり）のユーザーでログイン | E31: 1. mypageの「アカウント削除」を押す 2. 確認ダイアログで削除を確定する | F31: 処理完了後、サインアウトされ「/」（トップページ）へリダイレクトされる | G31: profile行・subscription行・script行（台本）がON DELETE CASCADEで削除される。Supabase Authのユーザーも削除される（管理画面/管理APIで確認） | H31: Stripeの顧客(customer)が削除される。顧客削除に伴い紐づくSubscriptionもcanceledになることを確認する | I31: - | J31: OK
A32: 31 | B32: DL-02 | C32: DL: ユーザー削除 | D32: フリープランのまま（一度も決済していない）ユーザーでログイン | E32: アカウント削除を実行する | F32: DL-01と同様に削除・リダイレクトされる | G32: profile行・subscription行・script行（台本）がON DELETE CASCADEで削除される。Supabase Authのユーザーも削除される（管理画面/管理APIで確認） | H32: Stripe顧客（サブスクリプションなし）が削除される | I32: - | J32: OK
A33: 32 | B33: DL-03 | C33: DL: ユーザー削除 | D33: 任意のログイン中ユーザー | E33: 「アカウント削除」→確認ダイアログで「キャンセル」を押す | F33: 何も起きず、mypage画面に留まる | G33: 変化なし | H33: 変化なし | I33: 誤操作防止の確認 | J33: OK
A34: 33 | B34: DL-04 | C34: DL: ユーザー削除 | D34: 次のいずれかを疑似的に再現する (a) ログインユーザー情報（getUserInfo）が取得できない (b) Stripeの顧客削除APIがresource_missing以外のエラーで失敗する（APIキーを一時的に無効化する等） | E34: アカウント削除を実行する | F34: 「ユーザー削除に失敗しました。しばらくしてからもう一度お試しください。」が表示される | G34: Authユーザー・profile・subscription・scriptのいずれも削除されない | H34: Stripe顧客が削除されない。Stripe顧客が残ったままAuthユーザーだけ消える不整合が起きていないこと | I34: Stripe顧客の削除に失敗した場合はAuthユーザーを削除しない（課金だけ残る事故を防ぐ）仕様の確認 | J34: OK | L34: supabaceのDB削除が失敗してもcatchに入らないから修正するべき
A35: 34 | B35: DL-05 | C35: DL: ユーザー削除 | D35: DL-01またはDL-02で削除済みのメールアドレス | E35: 同じメールアドレス・任意のパスワードで /sign-up から再登録する | F35: 「ユーザーはすでに存在しています。」等のエラーにならず、新規登録が正常に完了する | G35: 新しいuser_idでprofile/subscriptionが新規作成される（古いデータの残存がないこと） | H35: 新しいStripe顧客が作成される（削除前の顧客IDと重複しないこと） | I35: アカウント削除の完全性を確認する重要ケース | J35: OK
A36: 35 | B36: DL-06 | C36: DL: ユーザー削除 | D36: Stripeダッシュボードで、対象ユーザーのStripe顧客だけを先に削除しておく（前回のアカウント削除がAuthユーザー削除の手前で失敗した状態を再現） | E36: mypageからアカウント削除を実行する | F36: エラーにならず、サインアウトされて「/」へリダイレクトされる | G36: Authユーザー・profile・subscription・scriptが削除される | H36: 顧客は削除済みのまま（resource_missingエラーが返るが成功扱いになる） | I36: Stripe顧客の削除済み（resource_missing）を成功扱いにして、アカウント削除を再実行できることの確認 | J36: 未実施
A37: 36 | B37: WH-01 | C37: WH: Webhook確認 | D37: Stripe CLIがインストール済み、テストモードのAPIキーを.envに設定済み | E37: ローカル開発サーバー起動後、別ターミナルで `stripe listen --forward-to localhost:3000/api/stripe/webhook` を実行し、表示されたwebhook signing secretを STRIPE_WEBHOOK_SECRET に設定する | F37: - | G37: - | H37: Stripe CLIのログにイベントがforwardされ、200 OKが返っていることを確認 | I37: 全ての決済系テストの前提作業 | J37: OK
A38: 37 | B38: WH-02 | C38: WH: Webhook確認 | D38: WH-01の設定完了後、SU-02等で決済操作を行う | E38: サーバーログ（コンソール）を確認する | F38: - | G38: - | H38: checkout.session.completed / customer.subscription.created / customer.subscription.updated / customer.subscription.deleted / invoice.payment_succeeded / invoice.payment_failed の各イベントが想定通りのタイミングでログ出力されていることを確認 | I38: route.tsのswitch文のログ絵文字と合わせて確認すると分かりやすい | J38: OK
A39: 38 | B39: WH-03 | C39: WH: Webhook確認 | D39: 有料プラン契約済みユーザー | E39: mypageの「次回の支払い」または「解約予定日」の表示と、Stripeダッシュボード上のcurrent_period_endを見比べる | F39: 日本時間（ja-JP, Asia/Tokyo基準）で日時が正しく変換され表示されている | G39: subscription.current_period_endの文字列がロケール変換で崩れていないか確認 | H39: - | I39: toLocaleStringの変換ロジックの確認 | J39: OK
A40: 39 | B40: WH-04 | C40: WH: Webhook確認 | D40: 一連のテスト（SU/CH/CN/RE/DL）を一通り実施した後 | E40: Supabaseのprofile/subscriptionテーブルとStripeダッシュボード（顧客・サブスクリプション一覧）を突き合わせる | F40: - | G40: 孤児レコード（Stripe側は存在するがDBに無い、または逆）がないこと | H40: customer/subscriptionの件数・状態がDBと一致していること | I40: 全体テストの最終チェックとして実施 | J40: 未実施

Sheet ステージング（2026-10）
A1: No | B1: テストID | C1: 大分類 | D1: 前提条件 | E1: テスト手順 | F1: 期待結果（画面表示） | G1: 期待結果（DB: profile/subscription） | H1: 期待結果（Stripe側） | I1: 使用テストカード/備考 | J1: 実施結果 | K1: 実施日 | L1: 気づき・不具合メモ | M1: 実施環境
A2: 1 | B2: SU-01 | C2: SU: サインアップ・決済 | D2: 未登録のメールアドレスを準備する。/plan または /sign-up にアクセスできる状態。 | E2: 1. /plan の無料プランで「無料で始める」を押す（または直接 /sign-up） 2. メールアドレス・パスワードを入力し「新規登録」を送信 | F2: エラーなく /protected へ遷移する | G2: ・auth.usersにユーザーが作成される ・profileにstripe_uuid/supabase_uuid/emailが登録される ・subscriptionにplan_id=フリー, price_id=null, status='active', stripe_subscription_id=nullで1行作成される | H2: Stripeに顧客(customer)が作成される（サブスクリプションは作成されない） | I2: カード入力なし | J2: 未実施 | M2: ステージング
A3: 2 | B3: SU-02 | C3: SU: サインアップ・決済 | D3: 未ログイン状態。有料プランがStripeテストモードのPrice IDと紐づいて登録済みであること。 | E3: 1. /plan にアクセス（未ログイン） 2. 任意の有料プランの「今すぐ始める」を押す 3. /sign-up へ遷移することを確認し、メール・パスワードを入力して送信 4. Stripe Checkoutページでカード情報を入力し決済 | F3: 決済完了後、success_url（/protected?session_id=...）へリダイレクトされる。mypageのプラン表示が選択した有料プラン名になっている | G3: ・profile/subscription（フリー分）がまず作成される ・決済完了後、customer.subscription.created Webhookにより subscription 行が update され、plan_id=選択プラン, price_id, stripe_subscription_id, status='active', current_period_end, cancel_at_period_end=false になる | H3: Checkoutセッション完了、Subscriptionオブジェクトがactiveで作成される。metadata.user_idが正しく設定されていることを確認 | I3: 4242 4242 4242 4242（成功）／これが「planページからユーザー登録&決済」の本流フロー | J3: 未実施 | M3: ステージング
A4: 3 | B4: SU-03 | C4: SU: サインアップ・決済 | D4: SU-02と同じ手順の直前まで進める | E4: Checkoutページで拒否カードを入力して決済を試みる | F4: Stripe Checkout画面上にカードエラーが表示され、決済が完了しない。ユーザーはCheckout画面に留まる | G4: subscription行はフリープランのまま更新されない（Webhookが発火しないため） | H4: PaymentIntent/Charge が失敗する。Subscriptionは作成されない | I4: 4000 0000 0000 0002（決済拒否） | J4: 未実施 | M4: ステージング
A5: 4 | B5: SU-04 | C5: SU: サインアップ・決済 | D5: SU-02と同じ手順の直前まで進める | E5: Checkoutページで3Dセキュア認証が必要なカードを入力し、認証画面で認証を完了する | F5: 追加認証（3DS）画面が表示され、認証完了後に決済が成功し /protected へ遷移する | G5: customer.subscription.created Webhookにより subscription行が正しく更新される | H5: SubscriptionがactiveでStripe上に作成される | I5: 4000 0025 0000 3155（要3Dセキュア） | J5: 未実施 | M5: ステージング
A6: 5 | B6: SU-05 | C6: SU: サインアップ・決済 | D6: SU-02と同じ手順の直前まで進める | E6: Checkoutページでブラウザバック、または「戻る」リンクで決済をキャンセルする | F6: cancel_urlである /plan へリダイレクトされる。エラー表示は出ない | G6: ユーザー・profile・subscription（フリー分）は作成済みのまま。有料プランへは更新されない | H6: Checkoutセッションはexpired/未完了のまま。Subscriptionは作成されない | I6: - | J6: 未実施 | M6: ステージング
A7: 6 | B7: SU-06 | C7: SU: サインアップ・決済 | D7: 既に登録済みのメールアドレスを用意する | E7: そのメールアドレスで /sign-up から新規登録を試みる | F7: 「ユーザーはすでに存在しています。」がエラーメッセージとして表示される | G7: 新しいuser/profile/subscriptionは作成されない | H7: 新しいStripe顧客は作成されない | I7: - | J7: 未実施 | M7: ステージング
A8: 7 | B8: SU-07 | C8: SU: サインアップ・決済 | D8: - | E8: メールアドレスまたはパスワードを空欄のまま新規登録を送信する（フロントのバリデーションを回避できる場合も想定） | F8: 「メールアドレスとパスワードを入力してください。」等のエラーが表示される | G8: 何も作成されない | H8: 何も作成されない | I8: フォームのZodバリデーションと合わせて確認 | J8: 未実施 | M8: ステージング
A9: 8 | B9: SU-08 | C9: SU: サインアップ・決済 | D9: SU-01で作成したフリープランユーザーでログイン済み（＝「ユーザ作成後に決済」のケース） | E9: 1. ログイン状態で /plan（もしくはmypageの「プランを変更する」を経由せず直接）へアクセス 2. 有料プランの「このプランに変更する」を押す 3. Checkoutで決済を完了する | F9: 決済完了後 /protected へ遷移。mypageの現在のプランが有料プラン名に変わっている | G9: 既存のsubscription行（フリー分）がcustomer.subscription.created Webhookにより有料プラン情報でupdateされる（stripe_customer_idは既存のまま流用） | H9: 既存のcustomerに対してSubscriptionが新規作成される | I9: 4242 4242 4242 4242 | J9: 未実施 | M9: ステージング
A10: 9 | B10: SU-09 | C10: SU: サインアップ・決済 | D10: SU-08と同じ前提 | E10: ログイン済みユーザーが有料プラン決済を拒否カードで試みる | F10: Checkout画面でエラー表示、決済不成立 | G10: subscription行は更新されない（フリーのまま） | H10: Subscriptionは作成されない | I10: 4000 0000 0000 0002 | J10: 未実施 | M10: ステージング
A11: 10 | B11: SU-10 | C11: SU: サインアップ・決済 | D11: フリープランでログイン中。checkout()実行時にStripe API呼び出しが失敗する状況（テスト用に一時的にAPIキーを無効化する等で疑似的に再現） | E11: 有料プランの「このプランに変更する」を押す | F11: 「決済を開始できませんでした。時間をおいて再度お試しください。」がトースト表示される | G11: DBの状態は変化しない | H11: Checkoutセッションは作成されない | I11: 疑似障害での確認。本番同様の再現が難しい場合はコードレビューで代替可 | J11: 未実施 | M11: ローカル（疑似障害）
A12: 11 | B12: SU-11 | C12: SU: サインアップ・決済 | D12: 未ログイン状態で /sign-up を開く | E12: 1. メールアドレス・パスワードを入力し、同意のチェックボックスにチェックを入れずに「新規登録」を押す 2. 「利用規約」「プライバシーポリシー」のリンクを押す 3. チェックを入れて「新規登録」を押す | F12: ・1では「同意が必要です」と表示され、登録されない（チェックボックスが赤枠になる） ・2ではリンク先が別タブで開き、入力中のフォームの内容が消えない ・3では登録され /protected へ遷移する | G12: 1の時点では auth.users / profile / subscription が作成されない。3で作成される | H12: 1の時点では Stripe 顧客が作成されない | I12: サーバー側（signUpAction の signupSchema.safeParse）でも同意を検証している | J12: 未実施 | M12: ステージング
A13: 12 | B13: SU-12 | C13: SU: サインアップ・決済 | D13: (a) 未ログイン状態で /plan を開く (b) フリープランのユーザーでログインして /plan を開く | E13: 有料プランのボタン（(a)「今すぐ始める」／(b)「このプランに変更する」）を押し、表示された確認ダイアログを確認する。いったん「キャンセル」で閉じ、もう一度開いて確定ボタンを押す | F13: ・ダイアログに「料金（月額〇〇円・税込）」「お支払い（初回は申込時、以降は毎月の更新日に自動決済）」「契約期間（1か月ごとの自動更新）」「解約（マイページからいつでも可能、期間終了日まで利用可、途中解約の返金なし）」が表示される ・「利用規約」「プライバシーポリシー」のリンクが別タブで開く ・確定ボタンの文言が (a)「新規登録へ進む」／(b)「申し込む」 ・キャンセルで閉じた場合は何も起きない。確定すると (a) /sign-up へ、(b) Stripe Checkout へ遷移する | G13: 変化なし（確認ダイアログの表示確認） | H13: キャンセル時は Checkout セッションが作成されない | I13: 特定商取引法の最終確認画面としての表示確認 | J13: 未実施 | M13: ステージング
... A43: 42 | B43: WH-04 | C43: WH: Webhook確認 | D43: 一連のテスト（SU/CH/CN/RE/DL）を一通り実施した後 | E43: Supabaseのprofile/subscriptionテーブルとStripeダッシュボード（顧客・サブスクリプション一覧）を突き合わせる | F43: - | G43: 孤児レコード（Stripe側は存在するがDBに無い、または逆）がないこと | H43: customer/subscriptionの件数・状態がDBと一致していること | I43: 全体テストの最終チェックとして実施 | J43: 未実施 | M43: ステージング

Sheet 事前準備
B2: テスト実施前の準備
B4: ① Stripeテストモードの確認
B5: Stripeダッシュボード右上が「テスト環境」になっていること、アプリの環境変数のAPIキーが sk_test_ / pk_test_ から始まるテストモード用キーであることを確認する。本番キーで実施しないこと。
B7: ② Webhookのローカル転送
B8: Stripe CLIをインストールし、`stripe login` 後に以下を実行してWebhookをローカルに転送する。 stripe listen --forward-to localhost:3000/api/stripe/webhook 表示された whsec_... を環境変数 STRIPE_WEBHOOK_SECRET に設定してからサーバーを起動する。
B10: ③ 解約成立（期間終了）のテスト方法
B11: 実際の請求期間（1ヶ月等）を待たずに customer.subscription.deleted を発生させるには次のいずれかを使う。 ・Stripeの Test Clocks 機能でテスト用の時計を進めて期間終了を再現する（本来の流れ） ・Stripeダッシュボードでテスト用サブスクリプションを直接「今すぐキャンセル」する（簡易確認） ※ `stripe trigger customer.subscription.deleted` はダミーのサブスクリプションを作って削除するだけで、DBのsubscription行（stripe_subscription_id）と紐付かないため、代替にはならない
B13: ④ テストデータのクリーンアップ
B14: テストで作成したユーザー・Stripe顧客はテスト用であることが分かるようにし、テスト終了後は不要なテストユーザーをSupabase/Stripe双方から削除して環境を綺麗に保つ。
B16: ⑤ 確認に使うツール
B17: ・Stripeダッシュボード（テストモード）：顧客一覧・サブスクリプション詳細・イベントログ ・Supabaseダッシュボード：profile / subscription / plan テーブルの中身 ・ブラウザのDevTools：Server Actionのレスポンス、コンソールログ、Networkタブ
B19: ⑥ ステージング環境での実施（シート「ステージング（2026-10）」）
B20: ・Webhook は Stripe サンドボックスのエンドポイントからステージングに直接届くため、stripe listen は不要（WH-01 で設定を確認）。 ・Stripe のサンドボックスはローカルと共有しているため、テストユーザーは staging+01@... のようにステージング用と分かるメールアドレスにする。 ・疑似障害（APIキーを無効化する等）の5件は、環境変数の変更に再デプロイが必要なためローカルで実施する。 ・本番環境では、チェックリストとは別に少額での購入→解約の通し確認のみ行う（実際の決済が発生するため。確認後に返金）。

Sheet Stripeテストカード
A1: カード番号 | B1: 用途 | C1: 備考
A2: 4242 4242 4242 4242 | B2: 通常決済成功 | C2: 認証不要で即成功する最も基本のテストカード
A3: 4000 0025 0000 3155 | B3: 3Dセキュア（要認証） | C3: 認証ステップが挟まるフローの確認に使用
A4: 4000 0000 0000 9995 | B4: 残高不足で失敗 | C4: insufficient_fundsエラーの確認
A5: 4000 0000 0000 0002 | B5: カード拒否（generic decline） | C5: 決済失敗時のエラー表示確認
A6: 4000 0000 0000 0069 | B6: 有効期限切れ | C6: expired_cardエラーの確認
A7: 4000 0000 0000 0127 | B7: セキュリティコード不正 | C7: incorrect_cvcエラーの確認
A8: 4000 0000 0000 0119 | B8: 処理エラー（processing_error） | C8: Stripe側の一時的なエラーの確認
A11: ※ 上記以外のカード番号一覧は Stripe公式ドキュメント（Testing）を参照。有効期限は未来の任意の日付、CVCは任意の3桁、郵便番号は任意の値でよい。
